LICENSE
MANIFEST.in
README.rst
setup.cfg
setup.py
smbus_cffi_build.py
include/linux/i2c-dev.h
mysmbus.egg-info/PKG-INFO
mysmbus.egg-info/SOURCES.txt
mysmbus.egg-info/dependency_links.txt
mysmbus.egg-info/not-zip-safe
mysmbus.egg-info/requires.txt
mysmbus.egg-info/top_level.txt
smbus/__about__.py
smbus/__init__.py
smbus/smbus.py
smbus/smbusnew.py
smbus/util.py
test/test_smbus.py
test/test_smbus_integration.py
test/test_smbus_list.py
test/test_validator.py