Metadata-Version: 1.1
Name: mysmbus
Version: 0.1
Summary: This Python module allows SMBus access through the I2C /dev interface on Linux hosts. The host kernel must have I2C support, I2C device interface support, and a bus adapter driver.
Home-page: https://github.com/bivab/smbus-cffi
Author: David Schneider
Author-email: david.schneider@bivab.de
License: GPLv2
Platform: UNKNOWN
Classifier: License :: OSI Approved :: GNU General Public License v2 (GPLv2)
Classifier: Development Status :: 5 - Production/Stable
Classifier: Intended Audience :: Developers
Classifier: Intended Audience :: End Users/Desktop
Classifier: Intended Audience :: System Administrators
Classifier: Operating System :: POSIX :: Linux
Classifier: Programming Language :: Python :: 2.6
Classifier: Programming Language :: Python :: 2.7
Classifier: Programming Language :: Python :: 3
Classifier: Programming Language :: Python :: 3.2
Classifier: Programming Language :: Python :: 3.3
Classifier: Programming Language :: Python :: 3.4
Classifier: Programming Language :: Python :: Implementation :: CPython
Classifier: Programming Language :: Python :: Implementation :: PyPy
Classifier: Topic :: System :: Hardware
